<annotation>
	<folder>picture123</folder>
	<filename>232.jpg</filename>
	<path>C:\Users\xup61\Desktop\picture123\232.jpg</path>
	<source>
		<database>Unknown</database>
	</source>
	<size>
		<width>960</width>
		<height>540</height>
		<depth>3</depth>
	</size>
	<segmented>0</segmented>
	<object>
		<name>shrimp</name>
		<pose>Unspecified</pose>
		<truncated>0</truncated>
		<difficult>0</difficult>
		<robndbox>
			<cx>819.9505</cx>
			<cy>184.6816</cy>
			<w>48.7341</w>
			<h>158.082</h>
			<angle>2.1</angle>
		</robndbox>
		<extra/>
	</object>
	<object>
		<name>shrimp</name>
		<pose>Unspecified</pose>
		<truncated>0</truncated>
		<difficult>0</difficult>
		<robndbox>
			<cx>630.3624</cx>
			<cy>372.1493</cy>
			<w>37.3096</w>
			<h>122.6282</h>
			<angle>2.7</angle>
		</robndbox>
		<extra/>
	</object>
	<object>
		<name>shrimp</name>
		<pose>Unspecified</pose>
		<truncated>0</truncated>
		<difficult>0</difficult>
		<robndbox>
			<cx>417.3624</cx>
			<cy>111.1493</cy>
			<w>37.3096</w>
			<h>122.6282</h>
			<angle>2.0</angle>
		</robndbox>
		<extra/>
	</object>
	<object>
		<name>shrimp</name>
		<pose>Unspecified</pose>
		<truncated>0</truncated>
		<difficult>0</difficult>
		<robndbox>
			<cx>318.9448</cx>
			<cy>196.0873</cy>
			<w>37.9749</w>
			<h>127.8673</h>
			<angle>5.0</angle>
		</robndbox>
		<extra/>
	</object>
	<object>
		<name>shrimp</name>
		<pose>Unspecified</pose>
		<truncated>0</truncated>
		<difficult>0</difficult>
		<robndbox>
			<cx>175.9448</cx>
			<cy>181.0873</cy>
			<w>37.9749</w>
			<h>127.8673</h>
			<angle>5.5</angle>
		</robndbox>
		<extra/>
	</object>
	<object>
		<name>shrimp</name>
		<pose>Unspecified</pose>
		<truncated>0</truncated>
		<difficult>0</difficult>
		<robndbox>
			<cx>215.9448</cx>
			<cy>85.0873</cy>
			<w>37.9749</w>
			<h>127.8673</h>
			<angle>3.82</angle>
		</robndbox>
		<extra/>
	</object>
	<object>
		<name>shrimp</name>
		<pose>Unspecified</pose>
		<truncated>0</truncated>
		<difficult>0</difficult>
		<robndbox>
			<cx>99.3249</cx>
			<cy>97.7783</cy>
			<w>38.5298</w>
			<h>134.4761</h>
			<angle>0.716815</angle>
		</robndbox>
		<extra/>
	</object>
	<object>
		<name>shrimp</name>
		<pose>Unspecified</pose>
		<truncated>0</truncated>
		<difficult>0</difficult>
		<robndbox>
			<cx>144.9448</cx>
			<cy>251.0873</cy>
			<w>37.9749</w>
			<h>127.8673</h>
			<angle>1.416815</angle>
		</robndbox>
		<extra/>
	</object>
	<object>
		<name>shrimp</name>
		<pose>Unspecified</pose>
		<truncated>0</truncated>
		<difficult>0</difficult>
		<robndbox>
			<cx>811.7057</cx>
			<cy>49.1848</cy>
			<w>50.4789</w>
			<h>183.6363</h>
			<angle>1.8</angle>
		</robndbox>
		<extra/>
	</object>
</annotation>
